TypeTreeGeneratorAPI/TypeTreeGenerator.py
TypeTreeGeneratorAPI/__init__.py
TypeTreeGeneratorAPI/libTypeTreeGeneratorAPI.dylib
TypeTreeGeneratorAPI/libcapstone.dylib
typetreegeneratorapi-0.0.9.dist-info/licenses/LICENSE
typetreegeneratorapi-0.0.9.dist-info/METADATA
typetreegeneratorapi-0.0.9.dist-info/WHEEL
typetreegeneratorapi-0.0.9.dist-info/top_level.txt
typetreegeneratorapi-0.0.9.dist-info/RECORD
