Metadata-Version: 2.4
Name: TypeTreeGeneratorAPI
Version: 0.0.9
Summary: A Unity extraction and patching package
Author-email: Rudolf Kolbe <rkolbe96@gmail.com>
License: MIT License
Requires-Python: >=3.7
License-File: LICENSE
Provides-Extra: dev
Requires-Dist: ruff; extra == "dev"
Dynamic: license-file
